esotericai/__init__.py
esotericai/circuit.py
esotericai-0.0.2.dist-info/LICENSE
esotericai-0.0.2.dist-info/METADATA
esotericai-0.0.2.dist-info/WHEEL
esotericai-0.0.2.dist-info/top_level.txt
esotericai-0.0.2.dist-info/RECORD
