Metadata-Version: 2.2
Name: esotericai
Version: 0.0.2
Summary: Efficient distributed inference.
Home-page: https://github.com/esoteric-ai/esoteric-ai
Author: esoteric-ai
Author-email: kiselev.sereja@gmail.com
Classifier: Programming Language :: Python :: 3
Classifier: License :: OSI Approved :: MIT License
Classifier: Operating System :: OS Independent
Requires-Python: >=3.7
License-File: LICENSE
Requires-Dist: httpx
Requires-Dist: websockets
Dynamic: author
Dynamic: author-email
Dynamic: classifier
Dynamic: description
Dynamic: description-content-type
Dynamic: home-page
Dynamic: requires-dist
Dynamic: requires-python
Dynamic: summary
